[
  {
    "start": 0.1,
    "end": 5.81,
    "text": "Vue3 学习地图第五章讲了企微 JSAPI 的鉴权和专区接口。"
  },
  {
    "start": 5.76,
    "end": 11.19,
    "text": "这一章讲企微 H5 应用的另一大类能力，通用前端接口。"
  },
  {
    "start": 11.19,
    "end": 18.7,
    "text": "这些能力让你的网页能调用企微客户端的原生功能，就像微信 JS-SDK 一样。"
  },
  {
    "start": 18.7,
    "end": 32.46,
    "text": "前提要强调一遍，所有这些前端能力接口，调用之前都必须先调 ww dot register 注册身份成功，这是第五章的内容，没注册直接调都会失败。"
  },
  {
    "start": 32.46,
    "end": 34.36,
    "text": "一共五大类能力。"
  },
  {
    "start": 34.36,
    "end": 42.91,
    "text": "第一类是选人，接口叫 selectEnterpriseContact，可以选择企业通讯录里的成员、部门或标签。"
  },
  {
    "start": 42.91,
    "end": 46.21,
    "text": "这是企微特有的能力，微信没有。"
  },
  {
    "start": 46.21,
    "end": 52.81,
    "text": "参数里要指定选什么类型，是选成员还是选部门，是单选还是多选。"
  },
  {
    "start": 52.81,
    "end": 56.31,
    "text": "选完返回选中的人员或部门列表。"
  },
  {
    "start": 56.31,
    "end": 62.9,
    "text": "第二类是转发，接口叫 shareAppMessage，可以把消息转发到企微的会话里。"
  },
  {
    "start": 62.9,
    "end": 67.58,
    "text": "支持文本、图文、文本卡片等多种消息类型。"
  },
  {
    "start": 67.58,
    "end": 73.79,
    "text": "第三类是获取地理位置，接口叫 getLocation，拿到当前经纬度。"
  },
  {
    "start": 73.79,
    "end": 84.76,
    "text": "有个参数 type 决定坐标系，是 wgs八四还是 gcj零二，这个在国内开发要注意，gcj零二是火星坐标。"
  },
  {
    "start": 84.76,
    "end": 90.79,
    "text": "第四类是扫一扫，接口叫 scanQRCode，调起企微的扫码功能。"
  },
  {
    "start": 90.79,
    "end": 99.3,
    "text": "有个参数 needResult 决定扫码结果怎么处理，零是交给企微处理，一是返回给网页自己处理。"
  },
  {
    "start": 99.3,
    "end": 105.99,
    "text": "第五类是界面能力，包括设置导航栏标题颜色、关闭当前窗口这些。"
  },
  {
    "start": 105.99,
    "end": 109.16,
    "text": "最后说一下新旧两套调用方式。"
  },
  {
    "start": 109.16,
    "end": 119.76,
    "text": "旧版用 wx dot invoke 传接口名字符串，新版直接用 ww 点,接口名调用，官方推荐用新版更简洁。"
  },
  {
    "start": 119.76,
    "end": 123.41,
    "text": "不管新旧，前提都是 register 成功。"
  },
  {
    "start": 123.41,
    "end": 135.1,
    "text": "这一章记住一句话就够了：企微通用前端能力有五大类，选人转发定位扫码界面，所有接口调用前提都是 ww register 成功。"
  }
]